environ_odoo_config/__init__.py
environ_odoo_config/_odoo_command.py
environ_odoo_config/cli.py
environ_odoo_config/config_writer.py
environ_odoo_config/entrypoints.py
environ_odoo_config/environ.py
environ_odoo_config/odoo_config.py
environ_odoo_config/odoo_utils.py
environ_odoo_config/odoo_version.py
environ_odoo_config/utils.py
environ_odoo_config/config_section/__init__.py
environ_odoo_config/config_section/addons_path.py
environ_odoo_config/config_section/api.py
environ_odoo_config/config_section/database.py
environ_odoo_config/config_section/geo_ip_db.py
environ_odoo_config/config_section/gevent.py
environ_odoo_config/config_section/http.py
environ_odoo_config/config_section/i18n.py
environ_odoo_config/config_section/log.py
environ_odoo_config/config_section/misc.py
environ_odoo_config/config_section/other_option.py
environ_odoo_config/config_section/process_limit.py
environ_odoo_config/config_section/smtp.py
environ_odoo_config/config_section/test.py
environ_odoo_config/config_section/update_init.py
environ_odoo_config/config_section/wide_modules.py
environ_odoo_config/config_section/workers.py
environ_odoo_config/extension/__init__.py
environ_odoo_config/extension/auto_load_widemodules.py
environ_odoo_config/extension/auto_odoo_addon_path.py
environ_odoo_config/extension/db_max_conn_auto.py
environ_odoo_config/extension/postgresql_mapper.py
environ_odoo_config/extension/remove_addon_path.py
odoo/addons/environ_odoo_config/__init__.py
odoo/addons/environ_odoo_config/__manifest__.py
odoo/addons/environ_odoo_config/cli/__init__.py
odoo/addons/environ_odoo_config/cli/generate_config.py
odoo/addons/environ_odoo_config/cli/oenv2config.py
environ_odoo_config-0.6.5.dist-info/METADATA
environ_odoo_config-0.6.5.dist-info/WHEEL
environ_odoo_config-0.6.5.dist-info/entry_points.txt
environ_odoo_config-0.6.5.dist-info/RECORD
