Metadata-Version: 2.4
Name: environ-odoo-config
Version: 0.6.5
Classifier: Framework :: Odoo
Classifier: Framework :: Odoo :: 12.0
Classifier: Framework :: Odoo :: 13.0
Classifier: Framework :: Odoo :: 14.0
Classifier: Framework :: Odoo :: 15.0
Classifier: Framework :: Odoo :: 16.0
Classifier: Framework :: Odoo :: 17.0
Classifier: Framework :: Odoo :: 18.0
Classifier: Programming Language :: Python :: 3
Classifier: Programming Language :: Python :: 3 :: Only
Classifier: Programming Language :: Python :: 3.8
Classifier: Programming Language :: Python :: 3.9
Classifier: Programming Language :: Python :: 3.10
Classifier: Programming Language :: Python :: 3.11
Classifier: Programming Language :: Python :: 3.12
Classifier: Typing :: Typed
Requires-Python: >=3.8
Requires-Dist: get-annotations>=0.1.2; python_version < '3.10'
Requires-Dist: importlib-metadata>=6.7.0
Requires-Dist: python-dotenv==0.21.1; python_version == '3.7'
Requires-Dist: python-dotenv~=1.0; python_version > '3.7'
Requires-Dist: typing-extensions<5,>=4.3.0
